matchescu/data_sources/__init__.py
matchescu/data_sources/_csv.py
matchescu/extraction/__init__.py
matchescu/extraction/_base.py
matchescu/extraction/_record.py
matchescu/extraction/_samplers.py
matchescu/extraction/_traits.py
matchescu/py.typed
matchescu/references/__init__.py
matchescu/references/_record.py
matchescu_reference_extraction-0.7.3.dist-info/LICENSE
matchescu_reference_extraction-0.7.3.dist-info/METADATA
matchescu_reference_extraction-0.7.3.dist-info/WHEEL
matchescu_reference_extraction-0.7.3.dist-info/RECORD
