Metadata-Version: 2.1
Name: matchescu-reference-extraction
Version: 0.7.3
Summary: Extract references from a multitude of data sources
License: MIT
Author: Andrei Olar
Author-email: andrei.olar@samlex.ro
Requires-Python: >=3.12,<4.0
Classifier: License :: OSI Approved :: MIT License
Classifier: Programming Language :: Python :: 3
Classifier: Programming Language :: Python :: 3.12
Classifier: Programming Language :: Python :: 3.13
Requires-Dist: matchescu-base (>=0.22.1,<0.23.0)
Requires-Dist: polars (>=1.25.2,<2.0.0)
